README.rst
setup.py
retrypy/__init__.py
retrypy/check.py
retrypy/delay.py
retrypy/retry.py
retrypy.egg-info/PKG-INFO
retrypy.egg-info/SOURCES.txt
retrypy.egg-info/dependency_links.txt
retrypy.egg-info/top_level.txt
retrypy.egg-info/zip-safe
test/test_check.py
test/test_delay.py
test/test_retry.py