Metadata-Version: 1.0
Name: retrypy
Version: 0.0.33
Summary: Python retry utility
Home-page: https://github.com/toddsifleet/retrypy
Author: Todd Sifleet
Author-email: todd.siflet@gmail.com
License: MIT
Platform: UNKNOWN
